pofile/__init__.py
pofile/api/__init__.py
pofile/api/file.py
pofile/api/filename.py
pofile/core/FileType.py
pofile/core/SearchByContentType.py
pofile/core/__init__.py
pofile/lib/__init__.py
tests/__init__.py
tests/test_file.py
tests/test_files/__init__.py
tests/test_files/file/__init__.py
tests/test_files/file/add_fix/2插入内容0222022f插入内容dasfpp.py
tests/test_files/file/add_fix/__init__.py
pofile-0.1.5.dist-info/LICENSE
pofile-0.1.5.dist-info/METADATA
pofile-0.1.5.dist-info/WHEEL
pofile-0.1.5.dist-info/top_level.txt
pofile-0.1.5.dist-info/RECORD
